brainprint/__init__.py
brainprint/_version.py
brainprint/asymmetry.py
brainprint/brainprint.py
brainprint/surfaces.py
brainprint/cli/__init__.py
brainprint/cli/help_text.py
brainprint/cli/parser.py
brainprint/cli/utils.py
brainprint/commands/__init__.py
brainprint/commands/sys_info.py
brainprint/utils/__init__.py
brainprint/utils/_config.py
brainprint/utils/utils.py
brainprint-0.4.0.dist-info/LICENSE
brainprint-0.4.0.dist-info/METADATA
brainprint-0.4.0.dist-info/WHEEL
brainprint-0.4.0.dist-info/entry_points.txt
brainprint-0.4.0.dist-info/top_level.txt
brainprint-0.4.0.dist-info/RECORD
