Metadata-Version: 2.1
Name: brainprint
Version: 0.4.0
Summary: A package to compute BrainPrint (shape descriptors) from FastSurfer/FreeSurfer MRI segmentations
Author-email: Martin Reuter <martin.reuter@dzne.de>, Kersten Diers <kersten.diers@dzne.de>
Maintainer-email: Martin Reuter <martin.reuter@dzne.de>
License: MIT License
Project-URL: homepage, https://github.com/Deep-MI/BrainPrint
Project-URL: documentation, https://github.com/Deep-MI/BrainPrint
Project-URL: source, https://github.com/Deep-MI/BrainPrint
Project-URL: tracker, https://github.com/Deep-MI/BrainPrint/issues
Keywords: neuroscience,sMRI,FreeSurfer
Classifier: Operating System :: Microsoft :: Windows
Classifier: Operating System :: Unix
Classifier: Operating System :: MacOS
Classifier: Programming Language :: Python :: 3 :: Only
Classifier: Programming Language :: Python :: 3.8
Classifier: Programming Language :: Python :: 3.9
Classifier: Programming Language :: Python :: 3.10
Classifier: Programming Language :: Python :: 3.11
Classifier: Natural Language :: English
Classifier: License :: OSI Approved :: MIT License
Classifier: Intended Audience :: Science/Research
Requires-Python: >=3.8
License-File: LICENSE
Requires-Dist: numpy
Requires-Dist: scipy
Requires-Dist: pandas
Requires-Dist: lapy (<2,>=1.0.0)
Requires-Dist: psutil
Provides-Extra: all
Requires-Dist: brainprint[build] ; extra == 'all'
Requires-Dist: brainprint[doc] ; extra == 'all'
Requires-Dist: brainprint[style] ; extra == 'all'
Requires-Dist: brainprint[test] ; extra == 'all'
Provides-Extra: build
Requires-Dist: build ; extra == 'build'
Requires-Dist: twine ; extra == 'build'
Provides-Extra: full
Requires-Dist: brainprint[all] ; extra == 'full'
Provides-Extra: style
Requires-Dist: bibclean ; extra == 'style'
Requires-Dist: black ; extra == 'style'
Requires-Dist: codespell ; extra == 'style'
Requires-Dist: isort ; extra == 'style'
Requires-Dist: pydocstyle[toml] ; extra == 'style'
Requires-Dist: ruff ; extra == 'style'
Provides-Extra: test
Requires-Dist: pytest ; extra == 'test'
Requires-Dist: pytest-cov ; extra == 'test'
Requires-Dist: pytest-timeout ; extra == 'test'
